[
    {
      "img": "../assets/images/spotify-project.jpg",
      "alt": "Spotify Website Clone",
      "name": "Spotify Website UI Clone",
      "description":"Official website clone of Spotify using HTML,CSS and Javascript.",
      "button": "View Project",
      "href":"https://ibrahimgediktr.github.io/spotify-website-clone/"
    },
    {
      "img": "../assets/images/room-homapage-master.png",
      "alt": "Room Homepage Master",
      "name": "Room Homepage Master",
      "description":"A Frontend Mentor Challenge",
      "button": "View Project",
      "href":"https://room-homepage-master-lxnva5wub.vercel.app/"
    },
    {
      "img": "../assets/images/netflix-website-clone.png",
      "alt": "Netflix Website Frontend Clone",
      "name": "Netflix Website UI Clone",
      "description":"Official website clone of Netflix using React technology.",
      "button": "View Project",
      "href":"https://netflix-website-frontend-clone.netlify.app/"
    },
    {
      "img": "../assets/images/profile-card-component.png",
      "alt": "Profile Card Component",
      "name": "Profile Card Component?",
      "description":"A Frontend Mentor Challenge",
      "button": "View Project",
      "href":"https://profile-card-component.ibrahimgedik.vercel.app/"
    },
    {
      "img": "../assets/images/github-finder.png",
      "alt": "Github Finder",
      "name": "Github Finder",
      "description":"Search user and view repository using Github API.",
      "button": "View Project",
      "href":"https://ibrahimgediktr.github.io/github-finder/"
    },
    {
      "img": "../assets/images/faq-accordion-card.png",
      "alt": "FAQ Accordion Card",
      "name": "FAQ Accordion Card",
      "description":"A Frontend Mentor Challenge",
      "button": "View Project",
      "href":"https://faq-accordion-card-challenge.vercel.app/"
    },
    {
      "img": "../assets/images/sokaga-cikabilirmiyim.png",
      "alt": "Sokağa Çıkabilir miyim ?",
      "name": "Sokağa Çıkabilir miyim ?",
      "description":"The story of an algorithm that causes confusion.",
      "button": "View Project",
      "href":"https://sokaga-cikabilirmiyim-7etvxv1pe.vercel.app/"
    }
  ]
  